soundcloud/__init__.py
soundcloud/exceptions.py
soundcloud/py.typed
soundcloud/requests.py
soundcloud/soundcloud.py
soundcloud/resource/__init__.py
soundcloud/resource/aliases.py
soundcloud/resource/base.py
soundcloud/resource/base_item.py
soundcloud/resource/comment.py
soundcloud/resource/conversation.py
soundcloud/resource/download.py
soundcloud/resource/graphql.py
soundcloud/resource/history.py
soundcloud/resource/like.py
soundcloud/resource/message.py
soundcloud/resource/playlist.py
soundcloud/resource/response.py
soundcloud/resource/stream.py
soundcloud/resource/track.py
soundcloud/resource/user.py
soundcloud/resource/visuals.py
soundcloud/resource/web_profile.py
soundcloud_v2-1.6.1.dist-info/licenses/LICENSE
soundcloud_v2-1.6.1.dist-info/METADATA
soundcloud_v2-1.6.1.dist-info/WHEEL
soundcloud_v2-1.6.1.dist-info/top_level.txt
soundcloud_v2-1.6.1.dist-info/RECORD
